metalink/GPG.py
metalink/__init__.py
metalink/console.py
metalink/download.py
metalink/metalink.py
metalink/proxy.py
pymetalink-6.5.3.dist-info/AUTHORS.txt
pymetalink-6.5.3.dist-info/LICENSE.txt
pymetalink-6.5.3.dist-info/METADATA
pymetalink-6.5.3.dist-info/WHEEL
pymetalink-6.5.3.dist-info/entry_points.txt
pymetalink-6.5.3.dist-info/RECORD
