Metadata-Version: 2.1
Name: pymetalink
Version: 6.5.3
Summary: A metalink library for Python
Home-page: https://github.com/metalink-dev/pymetalink
License: MIT
Author: Neil McNab
Author-email: nabber00@gmail.com
Requires-Python: >=3.8,<4.0
Classifier: License :: OSI Approved :: MIT License
Classifier: Programming Language :: Python :: 3
Classifier: Programming Language :: Python :: 3.8
Classifier: Programming Language :: Python :: 3.9
Classifier: Programming Language :: Python :: 3.10
Classifier: Programming Language :: Python :: 3.11
Classifier: Programming Language :: Python :: 3.12
Classifier: Programming Language :: Python :: 3 :: Only
Classifier: Topic :: Internet :: WWW/HTTP
Classifier: Topic :: Software Development :: Libraries
Project-URL: Repository, https://github.com/metalink-dev/pymetalink
